nuheat/__init__.py
nuheat/api.py
nuheat/config.py
nuheat/thermostat.py
nuheat/util.py
nuheat-1.0.1.dist-info/LICENSE
nuheat-1.0.1.dist-info/METADATA
nuheat-1.0.1.dist-info/WHEEL
nuheat-1.0.1.dist-info/top_level.txt
nuheat-1.0.1.dist-info/RECORD
